pikvm_mouse_wiggle/__init__.py
pikvm_mouse_wiggle/main.py
pikvm_mouse_wiggle/wiggle.py
pikvm_mouse_wiggle/_internal/__init__.py
pikvm_mouse_wiggle/_internal/main.py
pikvm_mouse_wiggle-0.0.2.dist-info/LICENSE
pikvm_mouse_wiggle-0.0.2.dist-info/METADATA
pikvm_mouse_wiggle-0.0.2.dist-info/WHEEL
pikvm_mouse_wiggle-0.0.2.dist-info/entry_points.txt
pikvm_mouse_wiggle-0.0.2.dist-info/top_level.txt
pikvm_mouse_wiggle-0.0.2.dist-info/RECORD
