Metadata-Version: 2.1
Name: pikvm-mouse-wiggle
Version: 0.0.2
Summary: PI-KVM Mouse Wiggle
Home-page: https://github.com/jtyers/pikvm-mouse-wiggle
Author: Jonny Tyers
Author-email: jonny@jonnytyers.co.uk
License: MIT
Classifier: License :: OSI Approved :: MIT License
Classifier: Programming Language :: Python :: 3
Classifier: Programming Language :: Python :: 3.9
Classifier: Programming Language :: Python :: 3.10
License-File: LICENSE
